my_own_package/__init__.py
iulia_balan_own_package-0.1.0.dist-info/METADATA
iulia_balan_own_package-0.1.0.dist-info/WHEEL
iulia_balan_own_package-0.1.0.dist-info/top_level.txt
iulia_balan_own_package-0.1.0.dist-info/RECORD
