Metadata-Version: 2.1
Name: iulia-balan-own-package
Version: 0.1.0
Summary: my_first_package
Author: Iulia Balan
Author-email: denisabalan732@yahoo.com
